<?xml version="1.0" encoding="utf-8" ?><dwsync><file name="tess1.png" server="mathigon.org/public_html/private/world/" local="3450293383" remote="319783739094139588" Dst="-1" /><file name="tess10.png" server="mathigon.org/public_html/private/world/" local="3450293376" remote="319783739094139588" Dst="-1" /><file name="tess10@2x.png" server="mathigon.org/public_html/private/world/" local="3450293351" remote="319783739094139588" Dst="-1" /><file name="tess11.png" server="mathigon.org/public_html/private/world/" local="3450293378" remote="319783739094139588" Dst="-1" /><file name="tess11@2x.png" server="mathigon.org/public_html/private/world/" local="3450293357" remote="319783739094139588" Dst="-1" /><file name="tess1@2x.png" server="mathigon.org/public_html/private/world/" local="3450293369" remote="319783739094139588" Dst="-1" /><file name="tess2.png" server="mathigon.org/public_html/private/world/" local="3450980214" remote="319783739095252288" Dst="-1" /><file name="tess2@2x.png" server="mathigon.org/public_html/private/world/" local="3450293342" remote="319783739094139588" Dst="-1" /><file name="tess3.png" server="mathigon.org/public_html/private/world/" local="3450293382" remote="319783739094139588" Dst="-1" /><file name="tess3@2x.png" server="mathigon.org/public_html/private/world/" local="3450293373" remote="319783739094139588" Dst="-1" /><file name="tess4.png" server="mathigon.org/public_html/private/world/" local="3450293381" remote="319783739094139588" Dst="-1" /><file name="tess4@2x.png" server="mathigon.org/public_html/private/world/" local="3450293368" remote="319783739094139588" Dst="-1" /><file name="tess5.png" server="mathigon.org/public_html/private/world/" local="3450293380" remote="319783739094139588" Dst="-1" /><file name="tess5@2x.png" server="mathigon.org/public_html/private/world/" local="3450293362" remote="319783739094139588" Dst="-1" /><file name="tess6.png" server="mathigon.org/public_html/private/world/" local="3450293371" remote="319783739094139588" Dst="-1" /><file name="tess6@2x.png" server="mathigon.org/public_html/private/world/" local="3450293332" remote="319783739094139588" Dst="-1" /><file name="tess7.png" server="mathigon.org/public_html/private/world/" local="3450293379" remote="319783739094139588" Dst="-1" /><file name="tess7@2x.png" server="mathigon.org/public_html/private/world/" local="3450293351" remote="319783739094139588" Dst="-1" /><file name="tess8.png" server="mathigon.org/public_html/private/world/" local="3450293374" remote="319783739094139588" Dst="-1" /><file name="tess8@2x.png" server="mathigon.org/public_html/private/world/" local="3450293336" remote="319783739094139648" Dst="-1" /><file name="tess9.png" server="mathigon.org/public_html/private/world/" local="3450293375" remote="319783739094139648" Dst="-1" /><file name="tess9@2x.png" server="mathigon.org/public_html/private/world/" local="3450293344" remote="319783739094139648" Dst="-1" /><file name="tess1.png" server="mathigon.org/public_html/world/" local="3450293383" remote="319783739097720868" Dst="-1" /><file name="tess10.png" server="mathigon.org/public_html/world/" local="3450293376" remote="319783739097720868" Dst="-1" /><file name="tess10@2x.png" server="mathigon.org/public_html/world/" local="3450293351" remote="319783739097720868" Dst="-1" /><file name="tess11.png" server="mathigon.org/public_html/world/" local="3450293378" remote="319783739097720868" Dst="-1" /><file name="tess11@2x.png" server="mathigon.org/public_html/world/" local="3450293357" remote="319783739097720868" Dst="-1" /><file name="tess1@2x.png" server="mathigon.org/public_html/world/" local="3450293369" remote="319783739097720868" Dst="-1" /><file name="tess2.png" server="mathigon.org/public_html/world/" local="3450980214" remote="319783739097720868" Dst="-1" /><file name="tess2@2x.png" server="mathigon.org/public_html/world/" local="3450293342" remote="319783739097720868" Dst="-1" /><file name="tess3.png" server="mathigon.org/public_html/world/" local="3450293382" remote="319783739097720868" Dst="-1" /><file name="tess3@2x.png" server="mathigon.org/public_html/world/" local="3450293373" remote="319783739097720868" Dst="-1" /><file name="tess4.png" server="mathigon.org/public_html/world/" local="3450293381" remote="319783739097720868" Dst="-1" /><file name="tess4@2x.png" server="mathigon.org/public_html/world/" local="3450293368" remote="319783739097720868" Dst="-1" /><file name="tess5.png" server="mathigon.org/public_html/world/" local="3450293380" remote="319783739097720868" Dst="-1" /><file name="tess5@2x.png" server="mathigon.org/public_html/world/" local="3450293362" remote="319783739097720868" Dst="-1" /><file name="tess6.png" server="mathigon.org/public_html/world/" local="3450293371" remote="319783739097720868" Dst="-1" /><file name="tess6@2x.png" server="mathigon.org/public_html/world/" local="3450293332" remote="319783739097720868" Dst="-1" /><file name="tess7.png" server="mathigon.org/public_html/world/" local="3450293379" remote="319783739097720868" Dst="-1" /><file name="tess7@2x.png" server="mathigon.org/public_html/world/" local="3450293351" remote="319783739097720868" Dst="-1" /><file name="tess8.png" server="mathigon.org/public_html/world/" local="3450293374" remote="319783739097720868" Dst="-1" /><file name="tess8@2x.png" server="mathigon.org/public_html/world/" local="3450293336" remote="319783739097720868" Dst="-1" /><file name="tess9.png" server="mathigon.org/public_html/world/" local="3450293375" remote="319783739097720868" Dst="-1" /><file name="tess9@2x.png" server="mathigon.org/public_html/world/" local="3450293344" remote="319783739097720868" Dst="-1" /></dwsync>